tinamit_idm/__init__.py
tinamit_idm/puertos.py
tinamit_idm/puertos_asinc.py
tinamit_idm-0.2.4.dist-info/LICENSE
tinamit_idm-0.2.4.dist-info/WHEEL
tinamit_idm-0.2.4.dist-info/METADATA
tinamit_idm-0.2.4.dist-info/RECORD
