Metadata-Version: 2.1
Name: tinamit-idm
Version: 0.2.4
Summary: 
Author: joelz575
Author-email: joel.harms@mail.mcgill.ca
Requires-Python: >=3.8,<4.0
Classifier: Programming Language :: Python :: 3
Classifier: Programming Language :: Python :: 3.10
Classifier: Programming Language :: Python :: 3.8
Classifier: Programming Language :: Python :: 3.9
Requires-Dist: trio (>=0.19.0,<0.20.0)
